emiliaworks/__init__.py
emiliaworks/emilia.py
emiliaworks-0.3.5.dist-info/LICENSE
emiliaworks-0.3.5.dist-info/METADATA
emiliaworks-0.3.5.dist-info/WHEEL
emiliaworks-0.3.5.dist-info/top_level.txt
emiliaworks-0.3.5.dist-info/RECORD
