Metadata-Version: 2.1
Name: emiliaworks
Version: 0.3.5
Summary: Legitimacy Index
Home-page: https://github.com/revanthbugatti/Exhaustive-Modelling-of-Institutional-Legitimacy-of-International-Agencies---EMILIA-Index
Author: Revanth Uppalapati
Author-email: driftkingrev@gmail.com
License: UNKNOWN
Project-URL: Bug Tracker, https://github.com/revanthbugatti/Exhaustive-Modelling-of-Institutional-Legitimacy-of-International-Agencies---EMILIA-Index/issues
Platform: UNKNOWN
Classifier: Programming Language :: Python :: 3
Classifier: License :: OSI Approved :: MIT License
Classifier: Operating System :: OS Independent
Requires-Python: >=3.6
License-File: LICENSE
Requires-Dist: emoji
Requires-Dist: nltk
Requires-Dist: matplotlib
